mteo_util/__init__.py
mteo_util/bitmask.py
mteo_util/buffer.py
mteo_util/io.py
mteo_util/misc.py
mteo_util/os.py
mteo_util/random.py
mteo_util/socket.py
mteo_util/string.py
mteo_util/time.py
mteo_util/tlv.py
mteo_util/typing.py
mteo_util/version.py
mteo_util-0.0.2.dist-info/COPYING
mteo_util-0.0.2.dist-info/LICENSE
mteo_util-0.0.2.dist-info/METADATA
mteo_util-0.0.2.dist-info/WHEEL
mteo_util-0.0.2.dist-info/top_level.txt
mteo_util-0.0.2.dist-info/RECORD
