Metadata-Version: 2.1
Name: mteo-util
Version: 0.0.2
Summary: mteo's Python 3.x utility library
Home-page: https://github.com/mteofrancis/mteo-util
Author: Francis M
Author-email: mteofrancis@gmail.com
License: UNKNOWN
Project-URL: Bug Tracker, https://github.com/mteofrancis/mteo-util/issues
Platform: UNKNOWN
Classifier: Programming Language :: Python :: 3
Classifier: Development Status :: 3 - Alpha
Classifier: Topic :: Utilities
Classifier: License :: OSI Approved :: GNU General Public License v2 (GPLv2)
Requires-Python: >=3.8
License-File: LICENSE
License-File: COPYING
